{"asset":{"version":"1.0","extras":{"createdWith":"RealityCapture 1.3.1.117316"}},"geometricError":0.05499778,"root":{"boundingVolume":{"box":[31.31389809,15.47445679,28.45406342,1.04231834,0.0,0.0,0.0,0.34221649,0.0,0.0,0.0,0.99855709]},"geometricError":0.02890913,"refine":"REPLACE","content":{"url":"Geometry/lod1_77.b3dm"},"children":[{"boundingVolume":{"box":[30.73104858,15.40888405,27.98126411,0.44781303,0.0,0.0,0.0,0.2764883,0.0,0.0,0.0,0.52575874]},"geometricError":0.0,"refine":"REPLACE","content":{"url":"Geometry/lod0_304.b3dm"}},{"boundingVolume":{"box":[31.75292778,15.34019661,28.1289196,0.59450722,0.0,0.0,0.0,0.19611025,0.0,0.0,0.0,0.37810326]},"geometricError":0.0,"refine":"REPLACE","content":{"url":"Geometry/lod0_300.b3dm"}},{"boundingVolume":{"box":[30.78491592,15.61327648,28.89772415,0.50275803,0.0,0.0,0.0,0.2004137,0.0,0.0,0.0,0.47748184]},"geometricError":0.0,"refine":"REPLACE","content":{"url":"Geometry/lod0_308.b3dm"}},{"boundingVolume":{"box":[31.80679703,15.4857769,28.89772415,0.53955936,0.0,0.0,0.0,0.13162422,0.0,0.0,0.0,0.47748184]},"geometricError":0.0,"refine":"REPLACE","content":{"url":"Geometry/lod0_287.b3dm"}}]}}