{"asset":{"version":"1.0","extras":{"createdWith":"RealityCapture 1.3.1.117316"}},"geometricError":0.05621474,"root":{"boundingVolume":{"box":[37.49929047,24.80897331,29.44063187,0.54668427,0.0,0.0,0.0,1.09321785,0.0,0.0,0.0,1.38587379]},"geometricError":0.03089494,"refine":"REPLACE","content":{"url":"Geometry/lod1_93.b3dm"},"children":[{"boundingVolume":{"box":[37.2407608,25.42194748,28.97624207,0.28298569,0.0,0.0,0.0,0.46752262,0.0,0.0,0.0,0.91219711]},"geometricError":0.0,"refine":"REPLACE","content":{"url":"Geometry/lod0_364.b3dm"}},{"boundingVolume":{"box":[37.77672577,24.99140167,28.97624207,0.26369858,0.0,0.0,0.0,0.53081799,0.0,0.0,0.0,0.91219711]},"geometricError":0.0,"refine":"REPLACE","content":{"url":"Geometry/lod0_359.b3dm"}},{"boundingVolume":{"box":[37.23235321,24.98348236,30.33494186,0.27440643,0.0,0.0,0.0,0.65070629,0.0,0.0,0.0,0.47367859]},"geometricError":0.0,"refine":"REPLACE","content":{"url":"Geometry/lod0_362.b3dm"}},{"boundingVolume":{"box":[37.76831436,24.48560715,30.33494186,0.27227783,0.0,0.0,0.0,0.76224422,0.0,0.0,0.0,0.47367859]},"geometricError":0.0,"refine":"REPLACE","content":{"url":"Geometry/lod0_355.b3dm"}}]}}